[
  {
    "key": "hpfc",
    "component": "HPFC anchor",
    "duration_h": 1.0,
    "mean_m": 0.14195868898381547,
    "std_m": 0.03304010583648477,
    "p25_m": 0.11925156294052294,
    "p75_m": 0.16703677634318073,
    "pct_of_gross": 10.145322256619192
  },
  {
    "key": "da_surp",
    "component": "DA surprise",
    "duration_h": 1.0,
    "mean_m": 0.03656537447952099,
    "std_m": 0.03784715480292857,
    "p25_m": 0.010522509589632831,
    "p75_m": 0.052404236233063596,
    "pct_of_gross": 2.6132074773597918
  },
  {
    "key": "imbalance",
    "component": "Imbalance proxy (BM/ID substitute)",
    "duration_h": 1.0,
    "mean_m": 1.555712568287811,
    "std_m": 0.18042837096346892,
    "p25_m": 1.4191612159224933,
    "p75_m": 1.6680245323633287,
    "pct_of_gross": 111.18167867661806
  },
  {
    "key": "dc",
    "component": "DC ancillary",
    "duration_h": 1.0,
    "mean_m": 0.0,
    "std_m": 0.0,
    "p25_m": 0.0,
    "p75_m": 0.0,
    "pct_of_gross": 0.0
  },
  {
    "key": "qr",
    "component": "QR ancillary",
    "duration_h": 1.0,
    "mean_m": 0.5068781147573945,
    "std_m": 0.025724623623334227,
    "p25_m": 0.49064473949170995,
    "p75_m": 0.5254642249509657,
    "pct_of_gross": 36.22491765634476
  },
  {
    "key": "bm",
    "component": "Balancing Mechanism",
    "duration_h": 1.0,
    "mean_m": 0.17297164122511177,
    "std_m": 0.021912282512182513,
    "p25_m": 0.15908701838771816,
    "p75_m": 0.18642703946764466,
    "pct_of_gross": 12.361716313716766
  },
  {
    "key": "costs",
    "component": "Costs (deg+VOM)",
    "duration_h": 1.0,
    "mean_m": -0.5074168764711606,
    "std_m": 0.028284718713929465,
    "p25_m": -0.5284185820888869,
    "p75_m": -0.48482933203957496,
    "pct_of_gross": -36.263421190329275
  }
]